easycodronecommands/__init__.py
easycodronecommands/easydrone.py
EasyCodrone_EduCommands-0.0.7.dist-info/METADATA
EasyCodrone_EduCommands-0.0.7.dist-info/WHEEL
EasyCodrone_EduCommands-0.0.7.dist-info/top_level.txt
EasyCodrone_EduCommands-0.0.7.dist-info/RECORD
