Metadata-Version: 2.1
Name: EasyCodrone-EduCommands
Version: 0.0.7
Summary: Creates simple commands to be used with Codrone-edu
Home-page: https://github.com/burgerface627/EasyCodroneEduCommands
Author: Alex Birdsall
Author-email: burgerface627@outlook.com
License: MIT
Requires-Dist: codrone-edu
